odoo/addons/mrp_bom_current_stock/README.rst
odoo/addons/mrp_bom_current_stock/__init__.py
odoo/addons/mrp_bom_current_stock/__manifest__.py
odoo/addons/mrp_bom_current_stock/i18n/it.po
odoo/addons/mrp_bom_current_stock/i18n/mrp_bom_current_stock.pot
odoo/addons/mrp_bom_current_stock/i18n/tr.po
odoo/addons/mrp_bom_current_stock/readme/CONTRIBUTORS.md
odoo/addons/mrp_bom_current_stock/readme/DESCRIPTION.md
odoo/addons/mrp_bom_current_stock/readme/USAGE.md
odoo/addons/mrp_bom_current_stock/reports/__init__.py
odoo/addons/mrp_bom_current_stock/reports/report_mrpcurrentstock.xml
odoo/addons/mrp_bom_current_stock/reports/report_mrpcurrentstock_xlsx.py
odoo/addons/mrp_bom_current_stock/security/ir.model.access.csv
odoo/addons/mrp_bom_current_stock/static/description/icon.png
odoo/addons/mrp_bom_current_stock/static/description/index.html
odoo/addons/mrp_bom_current_stock/tests/__init__.py
odoo/addons/mrp_bom_current_stock/tests/test_mrp_bom_current_stock.py
odoo/addons/mrp_bom_current_stock/wizard/__init__.py
odoo/addons/mrp_bom_current_stock/wizard/bom_route_current_stock.py
odoo/addons/mrp_bom_current_stock/wizard/bom_route_current_stock_view.xml
odoo_addon_mrp_bom_current_stock-18.0.1.0.0.4.dist-info/METADATA
odoo_addon_mrp_bom_current_stock-18.0.1.0.0.4.dist-info/WHEEL
odoo_addon_mrp_bom_current_stock-18.0.1.0.0.4.dist-info/top_level.txt
odoo_addon_mrp_bom_current_stock-18.0.1.0.0.4.dist-info/RECORD
